pi_haiku/__init__.py
pi_haiku/haiku.py
pi_haiku/models.py
pi_haiku/py.typed
pi_haiku/pyproject_modifier.py
pi_haiku/utils/environment_detector.py
pi_haiku/utils/environment_utils.py
pi_haiku/utils/git_utils.py
pi_haiku/utils/github_utils.py
pi_haiku/utils/utils.py
pi_haiku-0.2.4.dist-info/METADATA
pi_haiku-0.2.4.dist-info/WHEEL
pi_haiku-0.2.4.dist-info/entry_points.txt
pi_haiku-0.2.4.dist-info/RECORD
