Metadata-Version: 2.1
Name: pi-haiku
Version: 0.2.4
Summary: 
Author: leeparnell
Author-email: 152523161+leeparnell@users.noreply.github.com
Requires-Python: >=3.11,<4.0
Classifier: Programming Language :: Python :: 3
Classifier: Programming Language :: Python :: 3.11
Classifier: Programming Language :: Python :: 3.12
Requires-Dist: gitpython (>=3.1.43,<4.0.0)
Requires-Dist: pi-conf (>=0.8.5.2,<0.9.0.0)
Requires-Dist: pydantic-settings (>=2.3.4,<3.0.0)
Requires-Dist: pygithub (>=2.3.0,<3.0.0)
Requires-Dist: requests (>=2.32.3,<3.0.0)
